setup.py
distributions/Binomialdistribution.py
distributions/Gaussiandistribution.py
distributions/Generaldistribution.py
distributions/__init__.py
menday.distributions.egg-info/PKG-INFO
menday.distributions.egg-info/SOURCES.txt
menday.distributions.egg-info/dependency_links.txt
menday.distributions.egg-info/not-zip-safe
menday.distributions.egg-info/top_level.txt