Metadata-Version: 1.0
Name: menday.distributions
Version: 0.1
Summary: Gaussian distributions
Home-page: UNKNOWN
Author: Stewart Menday
Author-email: stewart@menday.com.au
License: UNKNOWN
Platform: UNKNOWN
